fundata/__init__.py
fundata/dataset/__init__.py
fundata/dataset/core.py
fundata/dataset/datas.py
fundata/dataset/images.py
fundata/manage/__init__.py
fundata/manage/core.py
fundata/manage/library.py
fundata/paths/__init__.py
fundata/paths/core.py
fundata/tables_bak/__init__.py
fundata/tables_bak/core.py
fundata/work/__init__.py
fundata/work/core.py
fundata-1.0.1.dist-info/METADATA
fundata-1.0.1.dist-info/WHEEL
fundata-1.0.1.dist-info/top_level.txt
fundata-1.0.1.dist-info/RECORD
