Metadata-Version: 2.1
Name: fundata
Version: 1.0.1
Summary: Add your description here
Requires-Python: >=3.8
